passGJS25/src/PassGeJS25.py
passGJS25/src/__init__.py
passgejs25_workspace-0.0.4.dist-info/METADATA
passgejs25_workspace-0.0.4.dist-info/WHEEL
passgejs25_workspace-0.0.4.dist-info/top_level.txt
passgejs25_workspace-0.0.4.dist-info/RECORD
