Metadata-Version: 2.2
Name: passgejs25-workspace
Version: 0.0.4
Summary: A simple password generator
Requires-Python: >=3.12
